thds/tabularasa/__init__.py
thds/tabularasa/__main__.py
thds/tabularasa/compat.py
thds/tabularasa/git_util.py
thds/tabularasa/py.typed
thds/tabularasa/sqlite3_compat.py
thds/tabularasa/sqlite_from_parquet.py
thds/tabularasa/to_sqlite.py
thds/tabularasa/data_dependencies/__init__.py
thds/tabularasa/data_dependencies/adls.py
thds/tabularasa/data_dependencies/build.py
thds/tabularasa/data_dependencies/sqlite.py
thds/tabularasa/data_dependencies/tabular.py
thds/tabularasa/data_dependencies/util.py
thds/tabularasa/diff/__init__.py
thds/tabularasa/diff/data.py
thds/tabularasa/diff/schema.py
thds/tabularasa/diff/summary.py
thds/tabularasa/loaders/__init__.py
thds/tabularasa/loaders/lazy_adls.py
thds/tabularasa/loaders/parquet_util.py
thds/tabularasa/loaders/sqlite_util.py
thds/tabularasa/loaders/util.py
thds/tabularasa/schema/__init__.py
thds/tabularasa/schema/constraints.py
thds/tabularasa/schema/dtypes.py
thds/tabularasa/schema/extract_from_parquet.py
thds/tabularasa/schema/files.py
thds/tabularasa/schema/metaschema.py
thds/tabularasa/schema/util.py
thds/tabularasa/schema/validation.py
thds/tabularasa/schema/compilation/__init__.py
thds/tabularasa/schema/compilation/_format.py
thds/tabularasa/schema/compilation/attrs.py
thds/tabularasa/schema/compilation/attrs_sqlite.py
thds/tabularasa/schema/compilation/io.py
thds/tabularasa/schema/compilation/pandas.py
thds/tabularasa/schema/compilation/pyarrow.py
thds/tabularasa/schema/compilation/sphinx.py
thds/tabularasa/schema/compilation/sqlite.py
thds/tabularasa/schema/compilation/util.py
thds/tabularasa/testing/__init__.py
thds/tabularasa/testing/mock_sqlite.py
thds_tabularasa-0.14.3.dist-info/METADATA
thds_tabularasa-0.14.3.dist-info/WHEEL
thds_tabularasa-0.14.3.dist-info/entry_points.txt
thds_tabularasa-0.14.3.dist-info/top_level.txt
thds_tabularasa-0.14.3.dist-info/RECORD
