Metadata-Version: 2.4
Name: thds.tabularasa
Version: 0.14.3
Summary: Trilliant Health reference data build system.
Author-email: Trilliant Health <info@trillianthealth.com>
Project-URL: Repository, https://github.com/TrilliantHealth/ds-monorepo
Requires-Python: >=3.10
Requires-Dist: attrs>=22.2
Requires-Dist: cattrs>=22.2
Requires-Dist: filelock
Requires-Dist: networkx>=3.0
Requires-Dist: numpy
Requires-Dist: packaging
Requires-Dist: pandas>=1.5
Requires-Dist: pandera<0.24,>=0.20
Requires-Dist: pydantic<2.0,>=1.10.9
Requires-Dist: pyarrow>=10.0
Requires-Dist: pyyaml>=6.0.1
Requires-Dist: setuptools>=66.1.1
Requires-Dist: thds-adls
Requires-Dist: thds-core
Requires-Dist: typing-extensions
Provides-Extra: autoformat
Requires-Dist: black; extra == "autoformat"
Requires-Dist: isort; extra == "autoformat"
Provides-Extra: cli
Requires-Dist: bourbaki.application>=0.10.12; extra == "cli"
Requires-Dist: ruamel.yaml; extra == "cli"
Requires-Dist: tabulate; extra == "cli"
Requires-Dist: typing-inspect; extra == "cli"
Provides-Extra: viz
Requires-Dist: pygraphviz; extra == "viz"
